Metadata-Version: 1.0
Name: analogica-probability
Version: 1.2
Summary: Gaussian distributions and Binomial Distribution
Home-page: UNKNOWN
Author: Kartikay Sharma
Author-email: skartikay15@gmail.com
License: UNKNOWN
Platform: UNKNOWN
